{
  "project_info": {
    "project_number": "1016095914994",
    "project_id": "co-pet-d36b9",
    "storage_bucket": "co-pet-d36b9.appspot.com"
  },
  "client": [
    {
      "client_info": {
        "mobilesdk_app_id": "1:1016095914994:android:ea94a34ce011ab4aaf896b",
        "android_client_info": {
          "package_name": "com.example.co_pet"
        }
      },
      "oauth_client": [],
      "api_key": [
        {
          "current_key": "AIzaSyBAaVuaAiwcEQi0UnA_WTk580fNIa-Ve_E"
        }
      ],
      "services": {
        "appinvite_service": {
          "other_platform_oauth_client": []
        }
      }
    }
  ],
  "configuration_version": "1"
}